igdtools/__init__.py
igdtools/igdtools
igdtools/main.py
igdtools-2.5.dist-info/METADATA
igdtools-2.5.dist-info/WHEEL
igdtools-2.5.dist-info/entry_points.txt
igdtools-2.5.dist-info/top_level.txt
igdtools-2.5.dist-info/RECORD
