Metadata-Version: 2.4
Name: igdtools
Version: 2.5
Summary: Tools for converting VCF to IGD files and processing them.
Home-page: https://github.com/aprilweilab/picovcf
Author: Drew DeHaas
Author-email: 
Classifier: Programming Language :: Python :: 3
Classifier: Operating System :: MacOS
Classifier: Operating System :: POSIX :: Linux
Dynamic: author
Dynamic: classifier
Dynamic: description
Dynamic: description-content-type
Dynamic: home-page
Dynamic: summary
